botads/__init__.py
botads/async_client.py
botads/client.py
botads/constants.py
botads/errors.py
botads/webhook.py
botads_sdk-0.1.1.dist-info/METADATA
botads_sdk-0.1.1.dist-info/WHEEL
botads_sdk-0.1.1.dist-info/top_level.txt
botads_sdk-0.1.1.dist-info/RECORD
