Metadata-Version: 2.4
Name: botads-sdk
Version: 0.1.1
Summary: Botads Client API SDK for Python
Author: botads
License: MIT
Project-URL: Homepage, https://github.com/botads/botads
Classifier: Programming Language :: Python :: 3
Classifier: Programming Language :: Python :: 3.9
Classifier: Programming Language :: Python :: 3.10
Classifier: Programming Language :: Python :: 3.11
Classifier: Programming Language :: Python :: 3.12
Requires-Python: >=3.9
Requires-Dist: requests>=2.31.0
Requires-Dist: httpx>=0.27.0
